[
{"english":"amusement park",
"vietnamese":"phr công viên giải trí"},


{"english":"ancient history",
"vietnamese":"phr lịch sử cổ đại"},


{"english":"artifact",
"vietnamese":"n đồ tạo tác"},


{"english":"auditorium",
"vietnamese":"n khán phòng"},


{"english":"be booked up",
"vietnamese":"phr đã bán hết (vé, phòng)"},


{"english":"box office",
"vietnamese":"phr phòng vé"},


{"english":"cheerful",
"vietnamese":"adj vui mừng"},


{"english":"choir",
"vietnamese":"n đội hợp xướng, đội đồng ca"},


{"english":"entertain",
"vietnamese":"v giải trí, tiêu khiển"},


{"english":"flower arrangement",
"vietnamese":"phr cắm hoa"},


{"english":"flower bed",
"vietnamese":"n (phr) luống hoa"},


{"english":"go to a film",
"vietnamese":"phr đi xem phrm"},


{"english":"grip",
"vietnamese":"v nắm chặt, nắm vững"},


{"english":"have a race",
"vietnamese":"phr đua"},


{"english":"jog along the street",
"vietnamese":"phr chạy bộ dọc phố"},


{"english":"musical instrument",
"vietnamese":"phr nhạc cụ"},


{"english":"oar",
"vietnamese":"n mái chèo; v chèo thuyền; can thiệp"},


{"english":"oil painting",
"vietnamese":"phr tranh sơn dầu"},


{"english":"outdoor",
"vietnamese":"ad ngoài trời"},


{"english":"paddle",
"vietnamese":"v chèo thuyền; n mái chèo"},


{"english":"premiere",
"vietnamese":"n buổi ra mắt"},


{"english":"rake leaves",
"vietnamese":"phr cào lá"},


{"english":"recreational activity",
"vietnamese":"phr hoạt động giải trí"},


{"english":"right",
"vietnamese":"n quyền, lẽ phải; adj đúng, phải"},


{"english":"running time",
"vietnamese":"phr thời gian thực hiện"},


{"english":"sail a boat",
"vietnamese":"phr chèo thuyền"},


{"english":"slide down",
"vietnamese":"phr trượt xuống"},


{"english":"splash",
"vietnamese":"v bắn lên, tóe lên"},


{"english":"sport tournament",
"vietnamese":"phr giải thi đấu thể thao"},


{"english":"stadium",
"vietnamese":"n sân vận động"},


{"english":"stay up",
"vietnamese":"phr thức"},


{"english":"stroll",
"vietnamese":"v đi dạo"},


{"english":"take a break",
"vietnamese":"phr nghỉ ngơi"}


]
