[
{"english":"alleviate",
"vietnamese":"v. giảm bớt"},


{"english":"astrology",
"vietnamese":"n. thuật chiêm tinh, chiêm tinh học"},


{"english":"differentiate",
"vietnamese":"v. phân biệt"},


{"english":"disrupt",
"vietnamese":"v. làm gián đoạn"},


{"english":"equation",
"vietnamese":"n. phương trình"},


{"english":"err",
"vietnamese":"v. sai lầm"},


{"english":"erroneous",
"vietnamese":"adj. không đúng"},


{"english":"frantic",
"vietnamese":"adj. điên cuồng"},


{"english":"hull",
"vietnamese":"n. thân"},


{"english":"inadvertent",
"vietnamese":"adj. vô tình"},


{"english":"improvise",
"vietnamese":"v. ứng biến"},


{"english":"latitude",
"vietnamese":"n. vĩ độ"},


{"english":"mariner",
"vietnamese":"n. thủy thủ, lính thủy"},


{"english":"multitude",
"vietnamese":"n. đám đông, nhiều"},


{"english":"nuisance",
"vietnamese":"n. phiền toái"},


{"english":"permanence",
"vietnamese":"n. lâu dài"},


{"english":"revolve",
"vietnamese":"v. quay, xoay"},


{"english":"soothe",
"vietnamese":"v. xoa dịu"},


{"english":"stranded",
"vietnamese":"adj. bị mắc kẹt"},


{"english":"volatile",
"vietnamese":"adj. dễ biến động"}


]
